h2ctypes/common.py
h2ctypes/dump.py
h2ctypes/struct.py.j2
h2ctypes-0.1.3.dist-info/METADATA
h2ctypes-0.1.3.dist-info/WHEEL
h2ctypes-0.1.3.dist-info/entry_points.txt
h2ctypes-0.1.3.dist-info/top_level.txt
h2ctypes-0.1.3.dist-info/RECORD
