Metadata-Version: 2.4
Name: h2ctypes
Version: 0.1.3
Summary: convert c++ header files to python ctypes
Author-email: jwl <408066557@qq.com>
Requires-Python: >=3.10
Requires-Dist: jinja2>=3.1.6
Requires-Dist: typer>=0.19.1
